googletrans/__init__.py
googletrans/async_client.py
googletrans/client.py
googletrans/constants.py
googletrans/gtoken.py
googletrans/gtoken_async.py
googletrans/models.py
googletrans/urls.py
googletrans/utils.py
lds_pkg-0.1.2.dist-info/METADATA
lds_pkg-0.1.2.dist-info/WHEEL
lds_pkg-0.1.2.dist-info/top_level.txt
lds_pkg-0.1.2.dist-info/RECORD
